[
  {
    "cpf": "510.604.805-22",
    "nome": "M\u00E1rio Renan Cau\u00EA Ferreira",
    "data_nasc": "27/01/1951",
    "email": "mario-ferreira92@orbisat.com.br",
    "idade": 73,
    "rg": "20.737.304-8",
    "sexo": "Masculino",
    "signo": "Aqu\u00E1rio",
    "mae": "Jennifer Joana",
    "pai": "Caleb Leandro Nicolas Ferreira",
    "endereco": "Passeio das Castanheiras",
    "cidade": "S\u00E3o Carlos"
  },
  {
    "cpf": "581.232.961-34",
    "nome": "F\u00E1tima Pietra Santos",
    "data_nasc": "16/05/1970",
    "email": "fatima_pietra_santos@prcondominios.com.br",
    "idade": 54,
    "rg": "38.945.900-8",
    "sexo": "Feminino",
    "signo": "Touro",
    "mae": "Rayssa Clarice Allana",
    "pai": "Kau\u00EA Nathan Santos",
    "endereco": "Rua Agapito Magalh\u00E3es",
    "cidade": "Arapiraca"
  },
  {
    "cpf": "504.388.811-33",
    "nome": "Lu\u00EDs Julio Eduardo Ramos",
    "data_nasc": "04/06/1996",
    "email": "luisjulioramos@jarretta.com",
    "idade": 28,
    "rg": "10.151.765-8",
    "sexo": "Masculino",
    "signo": "G\u00EAmeos",
    "mae": "Heloise Isabela M\u00E1rcia",
    "pai": "Geraldo Guilherme Gustavo Ramos",
    "endereco": "Rua Vidal",
    "cidade": "Palho\u00E7a"
  },
  {
    "cpf": "438.804.468-73",
    "nome": "L\u00FAcia Milena Juliana de Paula",
    "data_nasc": "15/03/1959",
    "email": "lucia.milena.depaula@mv1.com.br",
    "idade": 65,
    "rg": "43.483.904-8",
    "sexo": "Feminino",
    "signo": "Peixes",
    "mae": "Analu Heloise",
    "pai": "Manoel Julio de Paula",
    "endereco": "Rua A-37",
    "cidade": "Macei\u00F3"
  },
  {
    "cpf": "072.189.338-40",
    "nome": "Tom\u00E1s Gustavo Diogo Souza",
    "data_nasc": "26/03/1986",
    "email": "tomas.gustavo.souza@tlmix.com.br",
    "idade": 38,
    "rg": "49.724.349-0",
    "sexo": "Masculino",
    "signo": "\u00C1ries",
    "mae": "Larissa Alessandra Alice",
    "pai": "Gael Yago Ben\u00EDcio Souza",
    "endereco": "Via de Pedestre 4",
    "cidade": "Fortaleza"
  },
  {
    "cpf": "288.391.527-09",
    "nome": "Vicente Renato Viana",
    "data_nasc": "06/06/1950",
    "email": "vicenterenatoviana@edepbr.com.br",
    "idade": 74,
    "rg": "46.608.446-8",
    "sexo": "Masculino",
    "signo": "G\u00EAmeos",
    "mae": "Silvana Carolina",
    "pai": "Manoel Benjamin F\u00E1bio Viana",
    "endereco": "Rua Ibirapuera",
    "cidade": "An\u00E1polis"
  },
  {
    "cpf": "620.422.978-87",
    "nome": "Raquel Milena Carolina da Concei\u00E7\u00E3o",
    "data_nasc": "08/05/2004",
    "email": "raquel_daconceicao@carvajal.com",
    "idade": 20,
    "rg": "27.443.707-7",
    "sexo": "Feminino",
    "signo": "Touro",
    "mae": "Aline Alana Heloisa",
    "pai": "Oliver Felipe Caio da Concei\u00E7\u00E3o",
    "endereco": "Vila Irm\u00E3os Pantoja",
    "cidade": "Bel\u00E9m"
  },
  {
    "cpf": "648.606.026-33",
    "nome": "Leandro Matheus Marcos Vinicius Alves",
    "data_nasc": "24/04/1957",
    "email": "leandro-alves94@contabilidadelibra.com.br",
    "idade": 67,
    "rg": "13.709.388-3",
    "sexo": "Masculino",
    "signo": "Touro",
    "mae": "Joana Joana Sara",
    "pai": "Pedro Henrique Roberto Andr\u00E9 Alves",
    "endereco": "Avenida Carlos Pereira de Melo",
    "cidade": "Boa Vista"
  },
  {
    "cpf": "433.337.363-81",
    "nome": "T\u00E2nia Ana Oliveira",
    "data_nasc": "26/01/1981",
    "email": "tania.ana.oliveira@technicolor.com",
    "idade": 43,
    "rg": "46.070.765-6",
    "sexo": "Feminino",
    "signo": "Aqu\u00E1rio",
    "mae": "Clara Simone Marlene",
    "pai": "Jorge Miguel Bernardo Oliveira",
    "endereco": "Avenida Ida Bianchi",
    "cidade": "Sinop"
  },
  {
    "cpf": "442.937.312-45",
    "nome": "Luciana Nina Caldeira",
    "data_nasc": "03/09/1987",
    "email": "luciana.nina.caldeira@granadaimoveis.com.br",
    "idade": 37,
    "rg": "10.217.110-5",
    "sexo": "Feminino",
    "signo": "Virgem",
    "mae": "Marina Bianca Raquel",
    "pai": "Kau\u00EA Enrico Caldeira",
    "endereco": "Avenida das Ac\u00E1cias",
    "cidade": "Cariacica"
  },
  {
    "cpf": "358.892.008-01",
    "nome": "string",
    "data_nasc": "string",
    "email": "string",
    "idade": 24,
    "rg": "string",
    "sexo": "string",
    "signo": "string",
    "mae": "string",
    "pai": "string",
    "endereco": "rua ponte",
    "cidade": "string"
  },
  {
    "cpf": "123.456.789-10",
    "nome": "string",
    "data_nasc": "string",
    "email": "string",
    "idade": 0,
    "rg": "string",
    "sexo": "string",
    "signo": "string",
    "mae": "string",
    "pai": "string",
    "endereco": "string",
    "cidade": "string"
  },
  {
    "cpf": "77788899955",
    "nome": "string",
    "data_nasc": "string",
    "email": "string",
    "idade": 0,
    "rg": "string",
    "sexo": "string",
    "signo": "string",
    "mae": "string",
    "pai": "string",
    "endereco": "string",
    "cidade": "string"
  },
  {
    "cpf": "ujguiguiguigui",
    "nome": "string",
    "data_nasc": "string",
    "email": "string",
    "idade": 0,
    "rg": "string",
    "sexo": "string",
    "signo": "string",
    "mae": "string",
    "pai": "string",
    "endereco": "string",
    "cidade": "string"
  }
]